rawio/__init__.py
rawio/version.py
rawio/align/__init__.py
rawio/align/constrain.py
rawio/align/exposures.py
rawio/align/level.py
rawio/align/vertical.py
rawio/grouping/__init__.py
rawio/grouping/group.py
rawio/grouping/markov.py
rawio/grouping/timestamp.py
rawio/grouping/wavelet.py
rawio/lens/__init__.py
rawio/lens/lens.py
rawio/lens/tca.py
rawio/raw/__init__.py
rawio/raw/lut.py
rawio/raw/metadata.py
rawio/raw/read.py
rawio/raw/data/raw_standard_med.tif
rawio-0.0.2.dist-info/LICENSE
rawio-0.0.2.dist-info/METADATA
rawio-0.0.2.dist-info/WHEEL
rawio-0.0.2.dist-info/top_level.txt
rawio-0.0.2.dist-info/RECORD
