Metadata-Version: 2.1
Name: rawio
Version: 0.0.2
Summary: RAW and raster image IO.
Home-page: https://github.com/hdkai/Raw-IO
Author: Yusuf Olokoba
Author-email: hi@hdk.ai
License: Apache License 2.0
Project-URL: Documentation, https://docs.hdk.ai/rawio
Project-URL: Source, https://github.com/hdkai/Raw-IO
Platform: UNKNOWN
Classifier: Programming Language :: Python :: 3
Classifier: License :: OSI Approved :: Apache Software License
Classifier: Operating System :: OS Independent
Classifier: Topic :: Scientific/Engineering :: Image Recognition
Classifier: Topic :: Software Development :: Libraries
Requires-Python: >=3.6
Requires-Dist: exifread
Requires-Dist: lensfunpy
Requires-Dist: imagehash
Requires-Dist: imageio
Requires-Dist: opencv-python-headless
Requires-Dist: piexif
Requires-Dist: pillow
Requires-Dist: python-dateutil
Requires-Dist: rawpy
Requires-Dist: scikit-learn
Requires-Dist: scipy
Requires-Dist: torch
Requires-Dist: torchvision
